{"v":"5.12.1","fr":30,"ip":0,"op":121,"w":394,"h":463,"nm":"Boxing","ddd":0,"assets":[],"layers":[{"ddd":0,"ind":1,"ty":4,"nm":"face","parent":4,"sr":1,"ks":{"o":{"a":0,"k":100,"ix":11},"r":{"a":0,"k":0,"ix":10},"p":{"a":0,"k":[-25.5,-66.625,0],"ix":2,"l":2},"a":{"a":0,"k":[-25.5,-66.625,0],"ix":1,"l":2},"s":{"a":0,"k":[100,100,100],"ix":6,"l":2}},"ao":0,"shapes":[{"ty":"gr","it":[{"d":1,"ty":"el","s":{"a":0,"k":[10.125,19.5],"ix":2},"p":{"a":0,"k":[0,0],"ix":3},"nm":"Ellipse Path 1","mn":"ADBE Vector Shape - Ellipse","hd":false,"_render":true},{"ty":"fl","c":{"a":0,"k":[0,0,0,1],"ix":4},"o":{"a":0,"k":100,"ix":5},"r":1,"bm":0,"nm":"Fill 1","mn":"ADBE Vector Graphic - Fill","hd":false,"_render":true},{"ty":"tr","p":{"a":0,"k":[10.688,-55.375],"ix":2},"a":{"a":0,"k":[0,0],"ix":1},"s":{"a":0,"k":[100,100],"ix":3},"r":{"a":0,"k":0,"ix":6},"o":{"a":0,"k":100,"ix":7},"sk":{"a":0,"k":0,"ix":4},"sa":{"a":0,"k":0,"ix":5},"nm":"Transform","_render":true}],"nm":"Ellipse 3","np":3,"cix":2,"bm":0,"ix":1,"mn":"ADBE Vector Group","hd":false,"_render":true},{"ty":"gr","it":[{"d":1,"ty":"el","s":{"a":0,"k":[10.75,10.75],"ix":2},"p":{"a":0,"k":[0,0],"ix":3},"nm":"Ellipse Path 1","mn":"ADBE Vector Shape - Ellipse","hd":false,"_render":true},{"ty":"fl","c":{"a":0,"k":[0,0,0,1],"ix":4},"o":{"a":0,"k":100,"ix":5},"r":1,"bm":0,"nm":"Fill 1","mn":"ADBE Vector Graphic - Fill","hd":false,"_render":true},{"ty":"tr","p":{"a":0,"k":[14.625,-82.25],"ix":2},"a":{"a":0,"k":[0,0],"ix":1},"s":{"a":1,"k":[{"i":{"x":[0.667,0.667],"y":[1,1]},"o":{"x":[0.333,0.333],"y":[0,0]},"t":19,"s":[100,100]},{"i":{"x":[0.667,0.667],"y":[1,1]},"o":{"x":[0.333,0.333],"y":[0,0]},"t":21,"s":[100,0]},{"i":{"x":[0.667,0.667],"y":[1,1]},"o":{"x":[0.298,0.298],"y":[0,0]},"t":23,"s":[100,100]},{"i":{"x":[0.667,0.667],"y":[1,1]},"o":{"x":[0.333,0.333],"y":[0,0]},"t":26,"s":[100,100]},{"i":{"x":[0.667,0.667],"y":[1,1]},"o":{"x":[0.333,0.333],"y":[0,0]},"t":28,"s":[100,0]},{"t":30,"s":[100,100]}],"ix":3},"r":{"a":0,"k":0,"ix":6},"o":{"a":0,"k":100,"ix":7},"sk":{"a":0,"k":0,"ix":4},"sa":{"a":0,"k":0,"ix":5},"nm":"Transform","_render":true}],"nm":"Ellipse 2","np":3,"cix":2,"bm":0,"ix":2,"mn":"ADBE Vector Group","hd":false,"_render":true},{"ty":"gr","it":[{"d":1,"ty":"el","s":{"a":0,"k":[10.75,10.75],"ix":2},"p":{"a":0,"k":[0,0],"ix":3},"nm":"Ellipse Path 1","mn":"ADBE Vector Shape - Ellipse","hd":false,"_render":true},{"ty":"fl","c":{"a":0,"k":[0,0,0,1],"ix":4},"o":{"a":0,"k":100,"ix":5},"r":1,"bm":0,"nm":"Fill 1","mn":"ADBE Vector Graphic - Fill","hd":false,"_render":true},{"ty":"tr","p":{"a":0,"k":[-20.125,-82.25],"ix":2},"a":{"a":0,"k":[0,0],"ix":1},"s":{"a":1,"k":[{"i":{"x":[0.667,0.667],"y":[1,1]},"o":{"x":[0.333,0.333],"y":[0,0]},"t":19,"s":[100,100]},{"i":{"x":[0.667,0.667],"y":[1,1]},"o":{"x":[0.333,0.333],"y":[0,0]},"t":21,"s":[100,0]},{"i":{"x":[0.667,0.667],"y":[1,1]},"o":{"x":[0.298,0.298],"y":[0,0]},"t":23,"s":[100,100]},{"i":{"x":[0.667,0.667],"y":[1,1]},"o":{"x":[0.333,0.333],"y":[0,0]},"t":26,"s":[100,100]},{"i":{"x":[0.667,0.667],"y":[1,1]},"o":{"x":[0.333,0.333],"y":[0,0]},"t":28,"s":[100,0]},{"t":30,"s":[100,100]}],"ix":3},"r":{"a":0,"k":0,"ix":6},"o":{"a":0,"k":100,"ix":7},"sk":{"a":0,"k":0,"ix":4},"sa":{"a":0,"k":0,"ix":5},"nm":"Transform","_render":true}],"nm":"Ellipse 1","np":3,"cix":2,"bm":0,"ix":3,"mn":"ADBE Vector Group","hd":false,"_render":true}],"ip":0,"op":180,"st":0,"ct":1,"bm":0,"completed":true},{"ddd":0,"ind":2,"ty":4,"nm":"l hand","parent":4,"sr":1,"ks":{"o":{"a":0,"k":100,"ix":11},"r":{"a":1,"k":[{"i":{"x":[0.667],"y":[1]},"o":{"x":[0.333],"y":[0]},"t":90,"s":[0]},{"i":{"x":[0.667],"y":[1]},"o":{"x":[0.333],"y":[0]},"t":93,"s":[11]},{"i":{"x":[0.667],"y":[1]},"o":{"x":[0.333],"y":[0]},"t":96,"s":[0]},{"i":{"x":[0.667],"y":[1]},"o":{"x":[0.333],"y":[0]},"t":99,"s":[11]},{"t":105,"s":[0]}],"ix":10},"p":{"a":0,"k":[62,-16.5,0],"ix":2,"l":2},"a":{"a":0,"k":[62,-16.5,0],"ix":1,"l":2},"s":{"a":0,"k":[100,100,100],"ix":6,"l":2}},"ao":0,"shapes":[{"ty":"gr","it":[{"ind":0,"ty":"sh","ix":1,"ks":{"a":1,"k":[{"i":{"x":0.667,"y":1},"o":{"x":0.333,"y":0},"t":0,"s":[{"i":[[-17.673,-32],[32,-17.673],[17.673,32],[-32,17.673]],"o":[[17.673,-32],[32,17.673],[-17.673,32],[-32,-17.673]],"v":[[0,-32],[32,0],[0,32],[-32,0]],"c":true}]},{"i":{"x":0.667,"y":1},"o":{"x":0.333,"y":0},"t":9,"s":[{"i":[[-26.923,-21.75],[22.75,-7.422999999999998],[8.422999999999998,42.25],[-41.25,27.923]],"o":[[8.422999999999998,-21.75],[22.75,27.923],[-26.923,42.25],[-41.25,-7.422999999999998]],"v":[[-9.25,-21.75],[22.75,10.25],[-9.25,42.25],[-41.25,10.25]],"c":true}]},{"i":{"x":0.667,"y":1},"o":{"x":0.333,"y":0},"t":15,"s":[{"i":[[-25.173,-16.5],[24.5,-2.1729999999999983],[10.172999999999998,47.5],[-39.5,33.173]],"o":[[10.172999999999998,-16.5],[24.5,33.173],[-25.173,47.5],[-39.5,-2.1729999999999983]],"v":[[-7.5,-16.5],[24.5,15.5],[-7.5,47.5],[-39.5,15.5]],"c":true}]},{"i":{"x":0.667,"y":1},"o":{"x":0.333,"y":0},"t":24,"s":[{"i":[[-17.923,-13.25],[31.75,1.0770000000000017],[17.423,50.75],[-32.25,36.423]],"o":[[17.423,-13.25],[31.75,36.423],[-17.923,50.75],[-32.25,1.0770000000000017]],"v":[[-0.25,-13.25],[31.75,18.75],[-0.25,50.75],[-32.25,18.75]],"c":true}]},{"i":{"x":0.667,"y":1},"o":{"x":0.333,"y":0},"t":30,"s":[{"i":[[-17.673,-32],[32,-17.673],[17.673,32],[-32,17.673]],"o":[[17.673,-32],[32,17.673],[-17.673,32],[-32,-17.673]],"v":[[0,-32],[32,0],[0,32],[-32,0]],"c":true}]},{"i":{"x":0.667,"y":1},"o":{"x":0.333,"y":0},"t":39,"s":[{"i":[[-26.923,-21.75],[22.75,-7.422999999999998],[8.422999999999998,42.25],[-41.25,27.923]],"o":[[8.422999999999998,-21.75],[22.75,27.923],[-26.923,42.25],[-41.25,-7.422999999999998]],"v":[[-9.25,-21.75],[22.75,10.25],[-9.25,42.25],[-41.25,10.25]],"c":true}]},{"i":{"x":0.667,"y":1},"o":{"x":0.333,"y":0},"t":45,"s":[{"i":[[-25.173,-16.5],[24.5,-2.1729999999999983],[10.172999999999998,47.5],[-39.5,33.173]],"o":[[10.172999999999998,-16.5],[24.5,33.173],[-25.173,47.5],[-39.5,-2.1729999999999983]],"v":[[-7.5,-16.5],[24.5,15.5],[-7.5,47.5],[-39.5,15.5]],"c":true}]},{"i":{"x":0.667,"y":1},"o":{"x":0.333,"y":0},"t":54,"s":[{"i":[[-17.923,-13.25],[31.75,1.0770000000000017],[17.423,50.75],[-32.25,36.423]],"o":[[17.423,-13.25],[31.75,36.423],[-17.923,50.75],[-32.25,1.0770000000000017]],"v":[[-0.25,-13.25],[31.75,18.75],[-0.25,50.75],[-32.25,18.75]],"c":true}]},{"i":{"x":0.667,"y":1},"o":{"x":0.333,"y":0},"t":60,"s":[{"i":[[-17.673,-32],[32,-17.673],[17.673,32],[-32,17.673]],"o":[[17.673,-32],[32,17.673],[-17.673,32],[-32,-17.673]],"v":[[0,-32],[32,0],[0,32],[-32,0]],"c":true}]},{"i":{"x":0.667,"y":1},"o":{"x":0.333,"y":0},"t":69,"s":[{"i":[[-26.923,-21.75],[22.75,-7.422999999999998],[8.422999999999998,42.25],[-41.25,27.923]],"o":[[8.422999999999998,-21.75],[22.75,27.923],[-26.923,42.25],[-41.25,-7.422999999999998]],"v":[[-9.25,-21.75],[22.75,10.25],[-9.25,42.25],[-41.25,10.25]],"c":true}]},{"i":{"x":0.667,"y":1},"o":{"x":0.333,"y":0},"t":75,"s":[{"i":[[-25.173,-16.5],[24.5,-2.1729999999999983],[10.172999999999998,47.5],[-39.5,33.173]],"o":[[10.172999999999998,-16.5],[24.5,33.173],[-25.173,47.5],[-39.5,-2.1729999999999983]],"v":[[-7.5,-16.5],[24.5,15.5],[-7.5,47.5],[-39.5,15.5]],"c":true}]},{"i":{"x":0.667,"y":1},"o":{"x":0.333,"y":0},"t":84,"s":[{"i":[[-17.923,-13.25],[31.75,1.0770000000000017],[17.423,50.75],[-32.25,36.423]],"o":[[17.423,-13.25],[31.75,36.423],[-17.923,50.75],[-32.25,1.0770000000000017]],"v":[[-0.25,-13.25],[31.75,18.75],[-0.25,50.75],[-32.25,18.75]],"c":true}]},{"i":{"x":0.833,"y":1},"o":{"x":0.333,"y":0},"t":90,"s":[{"i":[[-17.673,-32],[32,-17.673],[17.673,32],[-32,17.673]],"o":[[17.673,-32],[32,17.673],[-17.673,32],[-32,-17.673]],"v":[[0,-32],[32,0],[0,32],[-32,0]],"c":true}]},{"i":{"x":0.667,"y":1},"o":{"x":0.167,"y":0},"t":93,"s":[{"i":[[-87.923,-22.75],[-38.25,-8.422999999999998],[-52.577,41.25],[-102.25,26.923]],"o":[[-52.577,-22.75],[-38.25,26.923],[-87.923,41.25],[-102.25,-8.422999999999998]],"v":[[-70.25,-22.75],[-38.25,9.25],[-70.25,41.25],[-102.25,9.25]],"c":true}]},{"i":{"x":0.833,"y":1},"o":{"x":0.167,"y":0},"t":96,"s":[{"i":[[-17.673,-32],[32,-17.673],[17.673,32],[-32,17.673]],"o":[[17.673,-32],[32,17.673],[-17.673,32],[-32,-17.673]],"v":[[0,-32],[32,0],[0,32],[-32,0]],"c":true}]},{"i":{"x":0.667,"y":1},"o":{"x":0.167,"y":0},"t":99,"s":[{"i":[[-87.923,-22.75],[-38.25,-8.422999999999998],[-52.577,41.25],[-102.25,26.923]],"o":[[-52.577,-22.75],[-38.25,26.923],[-87.923,41.25],[-102.25,-8.422999999999998]],"v":[[-70.25,-22.75],[-38.25,9.25],[-70.25,41.25],[-102.25,9.25]],"c":true}]},{"i":{"x":0.667,"y":1},"o":{"x":0.167,"y":0},"t":105,"s":[{"i":[[-17.673,-32],[32,-17.673],[17.673,32],[-32,17.673]],"o":[[17.673,-32],[32,17.673],[-17.673,32],[-32,-17.673]],"v":[[0,-32],[32,0],[0,32],[-32,0]],"c":true}]},{"i":{"x":0.667,"y":1},"o":{"x":0.333,"y":0},"t":114,"s":[{"i":[[-17.923,-13.25],[31.75,1.0770000000000017],[17.423,50.75],[-32.25,36.423]],"o":[[17.423,-13.25],[31.75,36.423],[-17.923,50.75],[-32.25,1.0770000000000017]],"v":[[-0.25,-13.25],[31.75,18.75],[-0.25,50.75],[-32.25,18.75]],"c":true}]},{"t":120,"s":[{"i":[[-17.673,-32],[32,-17.673],[17.673,32],[-32,17.673]],"o":[[17.673,-32],[32,17.673],[-17.673,32],[-32,-17.673]],"v":[[0,-32],[32,0],[0,32],[-32,0]],"c":true}]}],"ix":2},"nm":"Path 1","mn":"ADBE Vector Shape - Group","hd":false,"_render":true},{"ty":"fl","c":{"a":0,"k":[0.1255,0.1529,0.1725,1],"ix":4},"o":{"a":0,"k":100,"ix":5},"r":1,"bm":0,"nm":"Fill 1","mn":"ADBE Vector Graphic - Fill","hd":false,"_render":true},{"ty":"tr","p":{"a":0,"k":[28.5,-7.5],"ix":2},"a":{"a":0,"k":[0,0],"ix":1},"s":{"a":0,"k":[100,100],"ix":3},"r":{"a":0,"k":0,"ix":6},"o":{"a":0,"k":100,"ix":7},"sk":{"a":0,"k":0,"ix":4},"sa":{"a":0,"k":0,"ix":5},"nm":"Transform","_render":true}],"nm":"Ellipse 1","np":3,"cix":2,"bm":0,"ix":1,"mn":"ADBE Vector Group","hd":false,"_render":true},{"ty":"gr","it":[{"ind":0,"ty":"sh","ix":1,"ks":{"a":1,"k":[{"i":{"x":0.667,"y":1},"o":{"x":0.333,"y":0},"t":0,"s":[{"i":[[58.625,-16.25],[72.469,-14.314],[91.704,3.2350000000000003],[83.75,40.875],[42.25,14.25]],"o":[[58.625,-16.25],[89,-1.75],[99.25,19.5],[55.867,27.886],[42.25,14.25]],"v":[[58.625,-16.25],[82.728,-6.517],[93.625,7.375],[63.625,31.5],[42.25,14.25]],"c":false}]},{"i":{"x":0.667,"y":1},"o":{"x":0.333,"y":0},"t":9,"s":[{"i":[[58.625,-16.25],[69.067,-12.901],[87.875,7.5],[73.75,47],[33,24.5]],"o":[[58.625,-16.25],[84.125,0],[89,24.378999999999998],[45.867,34.011],[33,24.5]],"v":[[58.625,-16.25],[78.853,-4.517],[88.125,11.25],[53.625,37.625],[33,24.5]],"c":false}]},{"i":{"x":0.667,"y":1},"o":{"x":0.333,"y":0},"t":15,"s":[{"i":[[58.625,-16.25],[70.942,-15.151],[89.138,6.667],[74.875,45.5],[39.375,27.5]],"o":[[58.625,-16.25],[86,-2.25],[92,24],[46.992,32.511],[39.375,27.5]],"v":[[58.625,-16.25],[80.728,-6.767],[89.75,10.375],[54.75,36.125],[39.375,27.5]],"c":false}]},{"i":{"x":0.667,"y":1},"o":{"x":0.333,"y":0},"t":24,"s":[{"i":[[58.625,-16.25],[73.25,-14],[95.388,6.667],[82.5,47.75],[46.625,30.75]],"o":[[58.625,-16.25],[89.79599999999999,-3.2300000000000004],[98.25,24],[52.626,35.02],[46.625,30.75]],"v":[[58.625,-16.25],[83.978,-7.017],[96,10.375],[60.5,38.375],[46.625,30.75]],"c":false}]},{"i":{"x":0.667,"y":1},"o":{"x":0.333,"y":0},"t":30,"s":[{"i":[[58.625,-16.25],[72.469,-14.314],[91.704,3.2350000000000003],[83.75,40.875],[42.25,14.25]],"o":[[58.625,-16.25],[89,-1.75],[99.25,19.5],[55.867,27.886],[42.25,14.25]],"v":[[58.625,-16.25],[82.728,-6.517],[93.625,7.375],[63.625,31.5],[42.25,14.25]],"c":false}]},{"i":{"x":0.667,"y":1},"o":{"x":0.333,"y":0},"t":39,"s":[{"i":[[58.625,-16.25],[69.067,-12.901],[87.875,7.5],[73.75,47],[33,24.5]],"o":[[58.625,-16.25],[84.125,0],[89,24.378999999999998],[45.867,34.011],[33,24.5]],"v":[[58.625,-16.25],[78.853,-4.517],[88.125,11.25],[53.625,37.625],[33,24.5]],"c":false}]},{"i":{"x":0.667,"y":1},"o":{"x":0.333,"y":0},"t":45,"s":[{"i":[[58.625,-16.25],[70.942,-15.151],[89.138,6.667],[74.875,45.5],[39.375,27.5]],"o":[[58.625,-16.25],[86,-2.25],[92,24],[46.992,32.511],[39.375,27.5]],"v":[[58.625,-16.25],[80.728,-6.767],[89.75,10.375],[54.75,36.125],[39.375,27.5]],"c":false}]},{"i":{"x":0.667,"y":1},"o":{"x":0.333,"y":0},"t":54,"s":[{"i":[[58.625,-16.25],[73.25,-14],[95.388,6.667],[82.5,47.75],[46.625,30.75]],"o":[[58.625,-16.25],[89.79599999999999,-3.2300000000000004],[98.25,24],[52.626,35.02],[46.625,30.75]],"v":[[58.625,-16.25],[83.978,-7.017],[96,10.375],[60.5,38.375],[46.625,30.75]],"c":false}]},{"i":{"x":0.667,"y":1},"o":{"x":0.333,"y":0},"t":60,"s":[{"i":[[58.625,-16.25],[72.469,-14.314],[91.704,3.2350000000000003],[83.75,40.875],[42.25,14.25]],"o":[[58.625,-16.25],[89,-1.75],[99.25,19.5],[55.867,27.886],[42.25,14.25]],"v":[[58.625,-16.25],[82.728,-6.517],[93.625,7.375],[63.625,31.5],[42.25,14.25]],"c":false}]},{"i":{"x":0.667,"y":1},"o":{"x":0.333,"y":0},"t":69,"s":[{"i":[[58.625,-16.25],[69.067,-12.901],[87.875,7.5],[73.75,47],[33,24.5]],"o":[[58.625,-16.25],[84.125,0],[89,24.378999999999998],[45.867,34.011],[33,24.5]],"v":[[58.625,-16.25],[78.853,-4.517],[88.125,11.25],[53.625,37.625],[33,24.5]],"c":false}]},{"i":{"x":0.667,"y":1},"o":{"x":0.333,"y":0},"t":75,"s":[{"i":[[58.625,-16.25],[70.942,-15.151],[89.138,6.667],[74.875,45.5],[39.375,27.5]],"o":[[58.625,-16.25],[86,-2.25],[92,24],[46.992,32.511],[39.375,27.5]],"v":[[58.625,-16.25],[80.728,-6.767],[89.75,10.375],[54.75,36.125],[39.375,27.5]],"c":false}]},{"i":{"x":0.667,"y":1},"o":{"x":0.333,"y":0},"t":84,"s":[{"i":[[58.625,-16.25],[73.25,-14],[95.388,6.667],[82.5,47.75],[46.625,30.75]],"o":[[58.625,-16.25],[89.79599999999999,-3.2300000000000004],[98.25,24],[52.626,35.02],[46.625,30.75]],"v":[[58.625,-16.25],[83.978,-7.017],[96,10.375],[60.5,38.375],[46.625,30.75]],"c":false}]},{"i":{"x":0.833,"y":1},"o":{"x":0.333,"y":0},"t":90,"s":[{"i":[[58.625,-16.25],[72.469,-14.314],[91.704,3.2350000000000003],[83.75,40.875],[42.25,14.25]],"o":[[58.625,-16.25],[89,-1.75],[99.25,19.5],[55.867,27.886],[42.25,14.25]],"v":[[58.625,-16.25],[82.728,-6.517],[93.625,7.375],[63.625,31.5],[42.25,14.25]],"c":false}]},{"i":{"x":0.667,"y":1},"o":{"x":0.167,"y":0},"t":93,"s":[{"i":[[58.625,-16.25],[55.028,-7.564],[38.945,10.369],[10.272,17.416999999999998],[-17,15]],"o":[[58.625,-16.25],[47.125,4.234999999999999],[19.713,16.855],[-7.705,16.566999999999997],[-17,15]],"v":[[58.625,-16.25],[50.978,-1.517],[32.625,12.5],[1.788,17.016],[-17,15]],"c":false}]},{"i":{"x":0.833,"y":1},"o":{"x":0.167,"y":0},"t":96,"s":[{"i":[[58.625,-16.25],[72.469,-14.314],[91.704,3.2350000000000003],[83.75,40.875],[42.25,14.25]],"o":[[58.625,-16.25],[89,-1.75],[99.25,19.5],[55.867,27.886],[42.25,14.25]],"v":[[58.625,-16.25],[82.728,-6.517],[93.625,7.375],[63.625,31.5],[42.25,14.25]],"c":false}]},{"i":{"x":0.667,"y":1},"o":{"x":0.167,"y":0},"t":99,"s":[{"i":[[58.625,-16.25],[55.028,-7.564],[38.945,10.369],[10.272,17.416999999999998],[-17,15]],"o":[[58.625,-16.25],[47.125,4.234999999999999],[19.713,16.855],[-7.705,16.566999999999997],[-17,15]],"v":[[58.625,-16.25],[50.978,-1.517],[32.625,12.5],[1.788,17.016],[-17,15]],"c":false}]},{"i":{"x":0.667,"y":1},"o":{"x":0.167,"y":0},"t":105,"s":[{"i":[[58.625,-16.25],[72.469,-14.314],[91.704,3.2350000000000003],[83.75,40.875],[42.25,14.25]],"o":[[58.625,-16.25],[89,-1.75],[99.25,19.5],[55.867,27.886],[42.25,14.25]],"v":[[58.625,-16.25],[82.728,-6.517],[93.625,7.375],[63.625,31.5],[42.25,14.25]],"c":false}]},{"i":{"x":0.667,"y":1},"o":{"x":0.333,"y":0},"t":114,"s":[{"i":[[58.625,-16.25],[73.25,-14],[95.388,6.667],[82.5,47.75],[46.625,30.75]],"o":[[58.625,-16.25],[89.79599999999999,-3.2300000000000004],[98.25,24],[52.626,35.02],[46.625,30.75]],"v":[[58.625,-16.25],[83.978,-7.017],[96,10.375],[60.5,38.375],[46.625,30.75]],"c":false}]},{"t":120,"s":[{"i":[[58.625,-16.25],[72.469,-14.314],[91.704,3.2350000000000003],[83.75,40.875],[42.25,14.25]],"o":[[58.625,-16.25],[89,-1.75],[99.25,19.5],[55.867,27.886],[42.25,14.25]],"v":[[58.625,-16.25],[82.728,-6.517],[93.625,7.375],[63.625,31.5],[42.25,14.25]],"c":false}]}],"ix":2},"nm":"Path 1","mn":"ADBE Vector Shape - Group","hd":false,"_render":true},{"ty":"st","c":{"a":0,"k":[0.2176,0.3371,0.4224,1],"ix":3},"o":{"a":0,"k":100,"ix":4},"w":{"a":0,"k":15,"ix":5},"lc":2,"lj":1,"ml":4,"bm":0,"nm":"Stroke 1","mn":"ADBE Vector Graphic - Stroke","hd":false,"_render":true},{"ty":"tr","p":{"a":0,"k":[0,0],"ix":2},"a":{"a":0,"k":[0,0],"ix":1},"s":{"a":0,"k":[100,100],"ix":3},"r":{"a":0,"k":0,"ix":6},"o":{"a":0,"k":100,"ix":7},"sk":{"a":0,"k":0,"ix":4},"sa":{"a":0,"k":0,"ix":5},"nm":"Transform","_render":true}],"nm":"Shape 1","np":3,"cix":2,"bm":0,"ix":2,"mn":"ADBE Vector Group","hd":false,"_render":true}],"ip":0,"op":180,"st":0,"ct":1,"bm":0,"completed":true},{"ddd":0,"ind":3,"ty":4,"nm":"band","parent":4,"sr":1,"ks":{"o":{"a":0,"k":100,"ix":11},"r":{"a":1,"k":[{"i":{"x":[0.667],"y":[1]},"o":{"x":[0.333],"y":[0]},"t":0,"s":[0]},{"i":{"x":[0.667],"y":[1]},"o":{"x":[0.333],"y":[0]},"t":15,"s":[-1]},{"i":{"x":[0.667],"y":[1]},"o":{"x":[0.297],"y":[0]},"t":30,"s":[0]},{"i":{"x":[0.667],"y":[1]},"o":{"x":[0.333],"y":[0]},"t":45,"s":[-1]},{"i":{"x":[0.667],"y":[1]},"o":{"x":[0.306],"y":[0]},"t":60,"s":[0]},{"i":{"x":[0.667],"y":[1]},"o":{"x":[0.333],"y":[0]},"t":75,"s":[-1]},{"i":{"x":[0.667],"y":[1]},"o":{"x":[0.297],"y":[0]},"t":90,"s":[0]},{"i":{"x":[0.667],"y":[1]},"o":{"x":[0.333],"y":[0]},"t":105,"s":[-1]},{"t":120,"s":[0]}],"ix":10},"p":{"a":1,"k":[{"i":{"x":0.667,"y":1},"o":{"x":0.333,"y":0},"t":0,"s":[6.75,-138.375,0],"to":[1.042,-0.167,0],"ti":[0,0,0]},{"i":{"x":0.667,"y":1},"o":{"x":0.333,"y":0},"t":15,"s":[13,-139.375,0],"to":[0,0,0],"ti":[1.042,-0.167,0]},{"i":{"x":0.667,"y":1},"o":{"x":0.333,"y":0},"t":30,"s":[6.75,-138.375,0],"to":null,"ti":null},{"i":{"x":0.667,"y":1},"o":{"x":0.333,"y":0},"t":45,"s":[13,-139.375,0],"to":[0,0,0],"ti":[1.042,-0.167,0]},{"i":{"x":0.667,"y":1},"o":{"x":0.324,"y":0},"t":60,"s":[6.75,-138.375,0],"to":null,"ti":null},{"i":{"x":0.667,"y":1},"o":{"x":0.333,"y":0},"t":75,"s":[13,-139.375,0],"to":[0,0,0],"ti":[1.042,-0.167,0]},{"i":{"x":0.667,"y":1},"o":{"x":0.333,"y":0},"t":90,"s":[6.75,-138.375,0],"to":null,"ti":null},{"i":{"x":0.667,"y":1},"o":{"x":0.333,"y":0},"t":105,"s":[13,-139.375,0],"to":[0,0,0],"ti":[1.042,-0.167,0]},{"t":120,"s":[6.75,-138.375,0]}],"ix":2,"l":2},"a":{"a":0,"k":[6.75,-138.375,0],"ix":1,"l":2},"s":{"a":0,"k":[100,100,100],"ix":6,"l":2}},"ao":0,"shapes":[{"ty":"gr","it":[{"ind":0,"ty":"sh","ix":1,"ks":{"a":0,"k":{"i":[[-59,-138.75],[72.5,-138]],"o":[[-59,-138.75],[72.5,-138]],"v":[[-59,-138.75],[72.5,-138]],"c":false},"ix":2},"nm":"Path 1","mn":"ADBE Vector Shape - Group","hd":false,"_render":true},{"ty":"st","c":{"a":0,"k":[0.1255,0.1529,0.1725,1],"ix":3},"o":{"a":0,"k":100,"ix":4},"w":{"a":0,"k":22,"ix":5},"lc":1,"lj":1,"ml":4,"bm":0,"nm":"Stroke 1","mn":"ADBE Vector Graphic - Stroke","hd":false,"_render":true},{"ty":"tr","p":{"a":0,"k":[0,0],"ix":2},"a":{"a":0,"k":[0,0],"ix":1},"s":{"a":0,"k":[100,100],"ix":3},"r":{"a":0,"k":0,"ix":6},"o":{"a":0,"k":100,"ix":7},"sk":{"a":0,"k":0,"ix":4},"sa":{"a":0,"k":0,"ix":5},"nm":"Transform","_render":true}],"nm":"Shape 1","np":3,"cix":2,"bm":0,"ix":1,"mn":"ADBE Vector Group","hd":false,"_render":true}],"ip":0,"op":180,"st":0,"ct":1,"bm":0,"completed":true},{"ddd":0,"ind":4,"ty":4,"nm":"body","sr":1,"ks":{"o":{"a":0,"k":100,"ix":11},"r":{"a":0,"k":0,"ix":10},"p":{"a":1,"k":[{"i":{"x":0.667,"y":1},"o":{"x":0.333,"y":0},"t":0,"s":[239.5,353.125,0],"to":null,"ti":null},{"i":{"x":0.667,"y":1},"o":{"x":0.333,"y":0},"t":9,"s":[239.5,332.625,0],"to":null,"ti":null},{"i":{"x":0.667,"y":1},"o":{"x":0.333,"y":0},"t":15,"s":[239.5,353.125,0],"to":null,"ti":null},{"i":{"x":0.667,"y":1},"o":{"x":0.333,"y":0},"t":24,"s":[239.5,334.875,0],"to":null,"ti":null},{"i":{"x":0.667,"y":1},"o":{"x":0.325,"y":0},"t":30,"s":[239.5,353.125,0],"to":null,"ti":null},{"i":{"x":0.667,"y":1},"o":{"x":0.333,"y":0},"t":39,"s":[239.5,332.625,0],"to":null,"ti":null},{"i":{"x":0.667,"y":1},"o":{"x":0.333,"y":0},"t":45,"s":[239.5,353.125,0],"to":null,"ti":null},{"i":{"x":0.667,"y":1},"o":{"x":0.333,"y":0},"t":54,"s":[239.5,334.875,0],"to":null,"ti":null},{"i":{"x":0.667,"y":1},"o":{"x":0.311,"y":0},"t":60,"s":[239.5,353.125,0],"to":null,"ti":null},{"i":{"x":0.667,"y":1},"o":{"x":0.333,"y":0},"t":69,"s":[239.5,332.625,0],"to":null,"ti":null},{"i":{"x":0.667,"y":1},"o":{"x":0.333,"y":0},"t":75,"s":[239.5,353.125,0],"to":null,"ti":null},{"i":{"x":0.667,"y":1},"o":{"x":0.333,"y":0},"t":84,"s":[239.5,334.875,0],"to":null,"ti":null},{"i":{"x":0.667,"y":1},"o":{"x":0.325,"y":0},"t":90,"s":[239.5,353.125,0],"to":null,"ti":null},{"i":{"x":0.667,"y":1},"o":{"x":0.333,"y":0},"t":99,"s":[239.5,332.625,0],"to":null,"ti":null},{"i":{"x":0.667,"y":1},"o":{"x":0.333,"y":0},"t":105,"s":[239.5,353.125,0],"to":null,"ti":null},{"i":{"x":0.667,"y":1},"o":{"x":0.333,"y":0},"t":114,"s":[239.5,334.875,0],"to":null,"ti":null},{"t":120,"s":[239.5,353.125,0]}],"ix":2,"l":2},"a":{"a":0,"k":[9.5,100.125,0],"ix":1,"l":2},"s":{"a":0,"k":[100,100,100],"ix":6,"l":2}},"ao":0,"shapes":[{"ty":"gr","it":[{"ind":0,"ty":"sh","ix":1,"ks":{"a":1,"k":[{"i":{"x":0.667,"y":1},"o":{"x":0.333,"y":0},"t":0,"s":[{"i":[[10.5,104.75],[8.248,-124.03],[4,-199.5]],"o":[[10.5,104.75],[7,-161],[4,-199.5]],"v":[[10.5,104.75],[7.793,-137.512],[4,-199.5]],"c":false}]},{"i":{"x":0.667,"y":1},"o":{"x":0.333,"y":0},"t":9,"s":[{"i":[[10.5,104.75],[11.181,-123.523],[13,-199.5]],"o":[[10.5,104.75],[11.5,-162],[13,-199.5]],"v":[[10.5,104.75],[11.293,-137.012],[13,-199.5]],"c":false}]},{"i":{"x":0.667,"y":1},"o":{"x":0.333,"y":0},"t":15,"s":[{"i":[[10.5,104.75],[12.238,-124.534],[17,-201]],"o":[[10.5,104.75],[13.75,-161.25],[17,-201]],"v":[[10.5,104.75],[12.793,-138.012],[17,-201]],"c":false}]},{"i":{"x":0.667,"y":1},"o":{"x":0.333,"y":0},"t":24,"s":[{"i":[[10.5,104.75],[9.693,-123.028],[8,-199.5]],"o":[[10.5,104.75],[8.5,-163.25],[8,-199.5]],"v":[[10.5,104.75],[9.293,-136.512],[8,-199.5]],"c":false}]},{"i":{"x":0.667,"y":1},"o":{"x":0.333,"y":0},"t":30,"s":[{"i":[[10.5,104.75],[8.248,-124.03],[4,-199.5]],"o":[[10.5,104.75],[7,-161],[4,-199.5]],"v":[[10.5,104.75],[7.793,-137.512],[4,-199.5]],"c":false}]},{"i":{"x":0.667,"y":1},"o":{"x":0.333,"y":0},"t":39,"s":[{"i":[[10.5,104.75],[11.181,-123.523],[13,-199.5]],"o":[[10.5,104.75],[11.5,-162],[13,-199.5]],"v":[[10.5,104.75],[11.293,-137.012],[13,-199.5]],"c":false}]},{"i":{"x":0.667,"y":1},"o":{"x":0.333,"y":0},"t":45,"s":[{"i":[[10.5,104.75],[12.238,-124.534],[17,-201]],"o":[[10.5,104.75],[13.75,-161.25],[17,-201]],"v":[[10.5,104.75],[12.793,-138.012],[17,-201]],"c":false}]},{"i":{"x":0.667,"y":1},"o":{"x":0.333,"y":0},"t":54,"s":[{"i":[[10.5,104.75],[9.693,-123.028],[8,-199.5]],"o":[[10.5,104.75],[8.5,-163.25],[8,-199.5]],"v":[[10.5,104.75],[9.293,-136.512],[8,-199.5]],"c":false}]},{"i":{"x":0.667,"y":1},"o":{"x":0.333,"y":0},"t":60,"s":[{"i":[[10.5,104.75],[8.248,-124.03],[4,-199.5]],"o":[[10.5,104.75],[7,-161],[4,-199.5]],"v":[[10.5,104.75],[7.793,-137.512],[4,-199.5]],"c":false}]},{"i":{"x":0.667,"y":1},"o":{"x":0.333,"y":0},"t":69,"s":[{"i":[[10.5,104.75],[11.181,-123.523],[13,-199.5]],"o":[[10.5,104.75],[11.5,-162],[13,-199.5]],"v":[[10.5,104.75],[11.293,-137.012],[13,-199.5]],"c":false}]},{"i":{"x":0.667,"y":1},"o":{"x":0.333,"y":0},"t":75,"s":[{"i":[[10.5,104.75],[12.238,-124.534],[17,-201]],"o":[[10.5,104.75],[13.75,-161.25],[17,-201]],"v":[[10.5,104.75],[12.793,-138.012],[17,-201]],"c":false}]},{"i":{"x":0.667,"y":1},"o":{"x":0.333,"y":0},"t":84,"s":[{"i":[[10.5,104.75],[9.693,-123.028],[8,-199.5]],"o":[[10.5,104.75],[8.5,-163.25],[8,-199.5]],"v":[[10.5,104.75],[9.293,-136.512],[8,-199.5]],"c":false}]},{"i":{"x":0.667,"y":1},"o":{"x":0.333,"y":0},"t":90,"s":[{"i":[[10.5,104.75],[8.248,-124.03],[4,-199.5]],"o":[[10.5,104.75],[7,-161],[4,-199.5]],"v":[[10.5,104.75],[7.793,-137.512],[4,-199.5]],"c":false}]},{"i":{"x":0.667,"y":1},"o":{"x":0.333,"y":0},"t":99,"s":[{"i":[[10.5,104.75],[11.181,-123.523],[13,-199.5]],"o":[[10.5,104.75],[11.5,-162],[13,-199.5]],"v":[[10.5,104.75],[11.293,-137.012],[13,-199.5]],"c":false}]},{"i":{"x":0.667,"y":1},"o":{"x":0.333,"y":0},"t":105,"s":[{"i":[[10.5,104.75],[12.238,-124.534],[17,-201]],"o":[[10.5,104.75],[13.75,-161.25],[17,-201]],"v":[[10.5,104.75],[12.793,-138.012],[17,-201]],"c":false}]},{"i":{"x":0.667,"y":1},"o":{"x":0.333,"y":0},"t":114,"s":[{"i":[[10.5,104.75],[9.693,-123.028],[8,-199.5]],"o":[[10.5,104.75],[8.5,-163.25],[8,-199.5]],"v":[[10.5,104.75],[9.293,-136.512],[8,-199.5]],"c":false}]},{"t":120,"s":[{"i":[[10.5,104.75],[8.248,-124.03],[4,-199.5]],"o":[[10.5,104.75],[7,-161],[4,-199.5]],"v":[[10.5,104.75],[7.793,-137.512],[4,-199.5]],"c":false}]}],"ix":2},"nm":"Path 1","mn":"ADBE Vector Shape - Group","hd":false,"_render":true},{"ty":"st","c":{"a":0,"k":[1,0.5569,0.2275,1],"ix":3},"o":{"a":0,"k":100,"ix":4},"w":{"a":0,"k":112,"ix":5},"lc":1,"lj":1,"ml":4,"bm":0,"nm":"Stroke 1","mn":"ADBE Vector Graphic - Stroke","hd":false,"_render":true},{"ty":"tr","p":{"a":0,"k":[0,0],"ix":2},"a":{"a":0,"k":[0,0],"ix":1},"s":{"a":0,"k":[100,100],"ix":3},"r":{"a":0,"k":0,"ix":6},"o":{"a":0,"k":100,"ix":7},"sk":{"a":0,"k":0,"ix":4},"sa":{"a":0,"k":0,"ix":5},"nm":"Transform","_render":true}],"nm":"Shape 1","np":3,"cix":2,"bm":0,"ix":1,"mn":"ADBE Vector Group","hd":false,"_render":true}],"ip":0,"op":180,"st":0,"ct":1,"bm":0,"completed":true},{"ddd":0,"ind":5,"ty":4,"nm":"r leg","sr":1,"ks":{"o":{"a":0,"k":100,"ix":11},"r":{"a":0,"k":0,"ix":10},"p":{"a":0,"k":[203,391,0],"ix":2,"l":2},"a":{"a":0,"k":[-27,138,0],"ix":1,"l":2},"s":{"a":0,"k":[100,100,100],"ix":6,"l":2}},"ao":0,"shapes":[{"ty":"gr","it":[{"ind":0,"ty":"sh","ix":1,"ks":{"a":1,"k":[{"i":{"x":0.667,"y":1},"o":{"x":0.333,"y":0},"t":0,"s":[{"i":[[-9.75,168.813],[-18.75,176.125],[-27,176.5]],"o":[[-9.75,168.813],[-18.75,176.125],[-27,176.5]],"v":[[-9.75,168.813],[-18.75,176.125],[-27,176.5]],"c":false}]},{"i":{"x":0.667,"y":1},"o":{"x":0.333,"y":0},"t":15,"s":[{"i":[[-11,176.688],[-18.75,176.625],[-27,176.5]],"o":[[-11,176.688],[-18.75,176.625],[-27,176.5]],"v":[[-11,176.688],[-18.75,176.625],[-27,176.5]],"c":false}]},{"i":{"x":0.667,"y":1},"o":{"x":0.333,"y":0},"t":30,"s":[{"i":[[-9.75,168.813],[-18.75,176.125],[-27,176.5]],"o":[[-9.75,168.813],[-18.75,176.125],[-27,176.5]],"v":[[-9.75,168.813],[-18.75,176.125],[-27,176.5]],"c":false}]},{"i":{"x":0.667,"y":1},"o":{"x":0.333,"y":0},"t":45,"s":[{"i":[[-11,176.688],[-18.75,176.625],[-27,176.5]],"o":[[-11,176.688],[-18.75,176.625],[-27,176.5]],"v":[[-11,176.688],[-18.75,176.625],[-27,176.5]],"c":false}]},{"i":{"x":0.667,"y":1},"o":{"x":0.333,"y":0},"t":60,"s":[{"i":[[-9.75,168.813],[-18.75,176.125],[-27,176.5]],"o":[[-9.75,168.813],[-18.75,176.125],[-27,176.5]],"v":[[-9.75,168.813],[-18.75,176.125],[-27,176.5]],"c":false}]},{"i":{"x":0.667,"y":1},"o":{"x":0.333,"y":0},"t":75,"s":[{"i":[[-11,176.688],[-18.75,176.625],[-27,176.5]],"o":[[-11,176.688],[-18.75,176.625],[-27,176.5]],"v":[[-11,176.688],[-18.75,176.625],[-27,176.5]],"c":false}]},{"i":{"x":0.667,"y":1},"o":{"x":0.333,"y":0},"t":90,"s":[{"i":[[-9.75,168.813],[-18.75,176.125],[-27,176.5]],"o":[[-9.75,168.813],[-18.75,176.125],[-27,176.5]],"v":[[-9.75,168.813],[-18.75,176.125],[-27,176.5]],"c":false}]},{"i":{"x":0.667,"y":1},"o":{"x":0.333,"y":0},"t":105,"s":[{"i":[[-11,176.688],[-18.75,176.625],[-27,176.5]],"o":[[-11,176.688],[-18.75,176.625],[-27,176.5]],"v":[[-11,176.688],[-18.75,176.625],[-27,176.5]],"c":false}]},{"t":120,"s":[{"i":[[-9.75,168.813],[-18.75,176.125],[-27,176.5]],"o":[[-9.75,168.813],[-18.75,176.125],[-27,176.5]],"v":[[-9.75,168.813],[-18.75,176.125],[-27,176.5]],"c":false}]}],"ix":2},"nm":"Path 1","mn":"ADBE Vector Shape - Group","hd":false,"_render":true},{"ty":"st","c":{"a":0,"k":[0.2176,0.3371,0.4224,1],"ix":3},"o":{"a":0,"k":100,"ix":4},"w":{"a":0,"k":5,"ix":5},"lc":2,"lj":1,"ml":4,"bm":0,"nm":"Stroke 1","mn":"ADBE Vector Graphic - Stroke","hd":false,"_render":true},{"ty":"tr","p":{"a":0,"k":[0,0],"ix":2},"a":{"a":0,"k":[0,0],"ix":1},"s":{"a":0,"k":[100,100],"ix":3},"r":{"a":0,"k":0,"ix":6},"o":{"a":0,"k":100,"ix":7},"sk":{"a":0,"k":0,"ix":4},"sa":{"a":0,"k":0,"ix":5},"nm":"Transform","_render":true}],"nm":"Shape 2","np":3,"cix":2,"bm":0,"ix":1,"mn":"ADBE Vector Group","hd":false,"_render":true},{"ty":"gr","it":[{"ind":0,"ty":"sh","ix":1,"ks":{"a":1,"k":[{"i":{"x":0.667,"y":1},"o":{"x":0.333,"y":0},"t":0,"s":[{"i":[[-21.25,70],[-24.25,120.875],[-12.5,171.25]],"o":[[-21.25,70],[-21.438,146.187],[-12.5,171.25]],"v":[[-21.25,70],[-22.375,137.75],[-12.5,171.25]],"c":false}]},{"i":{"x":0.667,"y":1},"o":{"x":0.333,"y":0},"t":15,"s":[{"i":[[-13.5,66.75],[-14,123],[-13.375,177.375]],"o":[[-13.5,66.75],[-13.432,147.987],[-13.375,177.375]],"v":[[-13.5,66.75],[-13.625,139.5],[-13.375,177.375]],"c":false}]},{"i":{"x":0.667,"y":1},"o":{"x":0.333,"y":0},"t":30,"s":[{"i":[[-21.25,70],[-24.25,120.875],[-12.5,171.25]],"o":[[-21.25,70],[-21.438,146.187],[-12.5,171.25]],"v":[[-21.25,70],[-22.375,137.75],[-12.5,171.25]],"c":false}]},{"i":{"x":0.667,"y":1},"o":{"x":0.333,"y":0},"t":45,"s":[{"i":[[-13.5,66.75],[-14,123],[-13.375,177.375]],"o":[[-13.5,66.75],[-13.432,147.987],[-13.375,177.375]],"v":[[-13.5,66.75],[-13.625,139.5],[-13.375,177.375]],"c":false}]},{"i":{"x":0.667,"y":1},"o":{"x":0.333,"y":0},"t":60,"s":[{"i":[[-21.25,70],[-24.25,120.875],[-12.5,171.25]],"o":[[-21.25,70],[-21.438,146.187],[-12.5,171.25]],"v":[[-21.25,70],[-22.375,137.75],[-12.5,171.25]],"c":false}]},{"i":{"x":0.667,"y":1},"o":{"x":0.333,"y":0},"t":75,"s":[{"i":[[-13.5,66.75],[-14,123],[-13.375,177.375]],"o":[[-13.5,66.75],[-13.432,147.987],[-13.375,177.375]],"v":[[-13.5,66.75],[-13.625,139.5],[-13.375,177.375]],"c":false}]},{"i":{"x":0.667,"y":1},"o":{"x":0.333,"y":0},"t":90,"s":[{"i":[[-21.25,70],[-24.25,120.875],[-12.5,171.25]],"o":[[-21.25,70],[-21.438,146.187],[-12.5,171.25]],"v":[[-21.25,70],[-22.375,137.75],[-12.5,171.25]],"c":false}]},{"i":{"x":0.667,"y":1},"o":{"x":0.333,"y":0},"t":105,"s":[{"i":[[-13.5,66.75],[-14,123],[-13.375,177.375]],"o":[[-13.5,66.75],[-13.432,147.987],[-13.375,177.375]],"v":[[-13.5,66.75],[-13.625,139.5],[-13.375,177.375]],"c":false}]},{"t":120,"s":[{"i":[[-21.25,70],[-24.25,120.875],[-12.5,171.25]],"o":[[-21.25,70],[-21.438,146.187],[-12.5,171.25]],"v":[[-21.25,70],[-22.375,137.75],[-12.5,171.25]],"c":false}]}],"ix":2},"nm":"Path 1","mn":"ADBE Vector Shape - Group","hd":false,"_render":true},{"ty":"st","c":{"a":0,"k":[0.2176,0.3371,0.4224,1],"ix":3},"o":{"a":0,"k":100,"ix":4},"w":{"a":0,"k":12,"ix":5},"lc":1,"lj":1,"ml":4,"bm":0,"nm":"Stroke 1","mn":"ADBE Vector Graphic - Stroke","hd":false,"_render":true},{"ty":"tr","p":{"a":0,"k":[0,0],"ix":2},"a":{"a":0,"k":[0,0],"ix":1},"s":{"a":0,"k":[100,100],"ix":3},"r":{"a":0,"k":0,"ix":6},"o":{"a":0,"k":100,"ix":7},"sk":{"a":0,"k":0,"ix":4},"sa":{"a":0,"k":0,"ix":5},"nm":"Transform","_render":true}],"nm":"Shape 1","np":3,"cix":2,"bm":0,"ix":2,"mn":"ADBE Vector Group","hd":false,"_render":true}],"ip":0,"op":180,"st":0,"ct":1,"bm":0,"completed":true},{"ddd":0,"ind":6,"ty":4,"nm":"l leg","sr":1,"ks":{"o":{"a":0,"k":94,"ix":11},"r":{"a":0,"k":0,"ix":10},"p":{"a":0,"k":[250.75,390.813,0],"ix":2,"l":2},"a":{"a":0,"k":[20.75,137.813,0],"ix":1,"l":2},"s":{"a":0,"k":[100,100,100],"ix":6,"l":2}},"ao":0,"shapes":[{"ty":"gr","it":[{"ind":0,"ty":"sh","ix":1,"ks":{"a":1,"k":[{"i":{"x":0.667,"y":1},"o":{"x":0.333,"y":0},"t":0,"s":[{"i":[[37.125,177.375],[27.06,177.375],[20.75,177.375]],"o":[[37.125,177.375],[27.06,177.375],[20.75,177.375]],"v":[[37.125,177.375],[27.06,177.375],[20.75,177.375]],"c":false}]},{"i":{"x":0.667,"y":1},"o":{"x":0.333,"y":0},"t":15,"s":[{"i":[[38.375,168.875],[28.454,177.405],[20.75,177.375]],"o":[[38.375,168.875],[28.454,177.405],[20.75,177.375]],"v":[[38.375,168.875],[28.454,177.405],[20.75,177.375]],"c":false}]},{"i":{"x":0.667,"y":1},"o":{"x":0.333,"y":0},"t":30,"s":[{"i":[[37.125,177.375],[27.06,177.375],[20.75,177.375]],"o":[[37.125,177.375],[27.06,177.375],[20.75,177.375]],"v":[[37.125,177.375],[27.06,177.375],[20.75,177.375]],"c":false}]},{"i":{"x":0.667,"y":1},"o":{"x":0.333,"y":0},"t":45,"s":[{"i":[[38.375,168.875],[28.454,177.405],[20.75,177.375]],"o":[[38.375,168.875],[28.454,177.405],[20.75,177.375]],"v":[[38.375,168.875],[28.454,177.405],[20.75,177.375]],"c":false}]},{"i":{"x":0.667,"y":1},"o":{"x":0.333,"y":0},"t":60,"s":[{"i":[[37.125,177.375],[27.06,177.375],[20.75,177.375]],"o":[[37.125,177.375],[27.06,177.375],[20.75,177.375]],"v":[[37.125,177.375],[27.06,177.375],[20.75,177.375]],"c":false}]},{"i":{"x":0.667,"y":1},"o":{"x":0.333,"y":0},"t":75,"s":[{"i":[[38.375,168.875],[28.454,177.405],[20.75,177.375]],"o":[[38.375,168.875],[28.454,177.405],[20.75,177.375]],"v":[[38.375,168.875],[28.454,177.405],[20.75,177.375]],"c":false}]},{"i":{"x":0.667,"y":1},"o":{"x":0.333,"y":0},"t":90,"s":[{"i":[[37.125,177.375],[27.06,177.375],[20.75,177.375]],"o":[[37.125,177.375],[27.06,177.375],[20.75,177.375]],"v":[[37.125,177.375],[27.06,177.375],[20.75,177.375]],"c":false}]},{"i":{"x":0.667,"y":1},"o":{"x":0.333,"y":0},"t":105,"s":[{"i":[[38.375,168.875],[28.454,177.405],[20.75,177.375]],"o":[[38.375,168.875],[28.454,177.405],[20.75,177.375]],"v":[[38.375,168.875],[28.454,177.405],[20.75,177.375]],"c":false}]},{"t":120,"s":[{"i":[[37.125,177.375],[27.06,177.375],[20.75,177.375]],"o":[[37.125,177.375],[27.06,177.375],[20.75,177.375]],"v":[[37.125,177.375],[27.06,177.375],[20.75,177.375]],"c":false}]}],"ix":2},"nm":"Path 1","mn":"ADBE Vector Shape - Group","hd":false,"_render":true},{"ty":"st","c":{"a":0,"k":[0.2176,0.3371,0.4224,1],"ix":3},"o":{"a":0,"k":100,"ix":4},"w":{"a":0,"k":5,"ix":5},"lc":2,"lj":1,"ml":4,"bm":0,"nm":"Stroke 1","mn":"ADBE Vector Graphic - Stroke","hd":false,"_render":true},{"ty":"tr","p":{"a":0,"k":[0,0],"ix":2},"a":{"a":0,"k":[0,0],"ix":1},"s":{"a":0,"k":[100,100],"ix":3},"r":{"a":0,"k":0,"ix":6},"o":{"a":0,"k":100,"ix":7},"sk":{"a":0,"k":0,"ix":4},"sa":{"a":0,"k":0,"ix":5},"nm":"Transform","_render":true}],"nm":"Shape 2","np":3,"cix":2,"bm":0,"ix":1,"mn":"ADBE Vector Group","hd":false,"_render":true},{"ty":"gr","it":[{"ind":0,"ty":"sh","ix":1,"ks":{"a":1,"k":[{"i":{"x":0.667,"y":1},"o":{"x":0.333,"y":0},"t":0,"s":[{"i":[[34.25,66.25],[33.948,132.238],[33.75,175.5]],"o":[[34.25,66.25],[33.948,132.238],[33.75,175.5]],"v":[[34.25,66.25],[33.948,132.238],[33.75,175.5]],"c":false}]},{"i":{"x":0.667,"y":1},"o":{"x":0.333,"y":0},"t":15,"s":[{"i":[[30.75,67.25],[23.75,118.75],[34.75,171.375]],"o":[[30.75,67.25],[24.905,132.482],[34.75,171.375]],"v":[[30.75,67.25],[24.465,127.25],[34.75,171.375]],"c":false}]},{"i":{"x":0.667,"y":1},"o":{"x":0.333,"y":0},"t":30,"s":[{"i":[[34.25,66.25],[33.948,132.238],[33.75,175.5]],"o":[[34.25,66.25],[33.948,132.238],[33.75,175.5]],"v":[[34.25,66.25],[33.948,132.238],[33.75,175.5]],"c":false}]},{"i":{"x":0.667,"y":1},"o":{"x":0.333,"y":0},"t":45,"s":[{"i":[[30.75,67.25],[23.75,118.75],[34.75,171.375]],"o":[[30.75,67.25],[24.905,132.482],[34.75,171.375]],"v":[[30.75,67.25],[24.465,127.25],[34.75,171.375]],"c":false}]},{"i":{"x":0.667,"y":1},"o":{"x":0.333,"y":0},"t":60,"s":[{"i":[[34.25,66.25],[33.948,132.238],[33.75,175.5]],"o":[[34.25,66.25],[33.948,132.238],[33.75,175.5]],"v":[[34.25,66.25],[33.948,132.238],[33.75,175.5]],"c":false}]},{"i":{"x":0.667,"y":1},"o":{"x":0.333,"y":0},"t":75,"s":[{"i":[[30.75,67.25],[23.75,118.75],[34.75,171.375]],"o":[[30.75,67.25],[24.905,132.482],[34.75,171.375]],"v":[[30.75,67.25],[24.465,127.25],[34.75,171.375]],"c":false}]},{"i":{"x":0.667,"y":1},"o":{"x":0.333,"y":0},"t":90,"s":[{"i":[[34.25,66.25],[33.948,132.238],[33.75,175.5]],"o":[[34.25,66.25],[33.948,132.238],[33.75,175.5]],"v":[[34.25,66.25],[33.948,132.238],[33.75,175.5]],"c":false}]},{"i":{"x":0.667,"y":1},"o":{"x":0.333,"y":0},"t":105,"s":[{"i":[[30.75,67.25],[23.75,118.75],[34.75,171.375]],"o":[[30.75,67.25],[24.905,132.482],[34.75,171.375]],"v":[[30.75,67.25],[24.465,127.25],[34.75,171.375]],"c":false}]},{"t":120,"s":[{"i":[[34.25,66.25],[33.948,132.238],[33.75,175.5]],"o":[[34.25,66.25],[33.948,132.238],[33.75,175.5]],"v":[[34.25,66.25],[33.948,132.238],[33.75,175.5]],"c":false}]}],"ix":2},"nm":"Path 1","mn":"ADBE Vector Shape - Group","hd":false,"_render":true},{"ty":"st","c":{"a":0,"k":[0.2176,0.3371,0.4224,1],"ix":3},"o":{"a":0,"k":100,"ix":4},"w":{"a":0,"k":12,"ix":5},"lc":1,"lj":1,"ml":4,"bm":0,"nm":"Stroke 1","mn":"ADBE Vector Graphic - Stroke","hd":false,"_render":true},{"ty":"tr","p":{"a":0,"k":[0,0],"ix":2},"a":{"a":0,"k":[0,0],"ix":1},"s":{"a":0,"k":[100,100],"ix":3},"r":{"a":0,"k":0,"ix":6},"o":{"a":0,"k":100,"ix":7},"sk":{"a":0,"k":0,"ix":4},"sa":{"a":0,"k":0,"ix":5},"nm":"Transform","_render":true}],"nm":"Shape 1","np":3,"cix":2,"bm":0,"ix":2,"mn":"ADBE Vector Group","hd":false,"_render":true}],"ip":0,"op":180,"st":0,"ct":1,"bm":0,"completed":true},{"ddd":0,"ind":7,"ty":4,"nm":"r hand","parent":4,"sr":1,"ks":{"o":{"a":0,"k":100,"ix":11},"r":{"a":0,"k":0,"ix":10},"p":{"a":0,"k":[-92.5,9.735,0],"ix":2,"l":2},"a":{"a":0,"k":[-92.5,9.735,0],"ix":1,"l":2},"s":{"a":0,"k":[100,100,100],"ix":6,"l":2}},"ao":0,"shapes":[{"ty":"gr","it":[{"ind":0,"ty":"sh","ix":1,"ks":{"a":1,"k":[{"i":{"x":0.667,"y":1},"o":{"x":0.333,"y":0},"t":0,"s":[{"i":[[-17.673,-32],[32,-17.673],[17.673,32],[-32,17.673]],"o":[[17.673,-32],[32,17.673],[-17.673,32],[-32,-17.673]],"v":[[0,-32],[32,0],[0,32],[-32,0]],"c":true}]},{"i":{"x":0.667,"y":1},"o":{"x":0.333,"y":0},"t":15,"s":[{"i":[[-17.673,-13.5],[32,0.8270000000000017],[17.673,50.5],[-32,36.173]],"o":[[17.673,-13.5],[32,36.173],[-17.673,50.5],[-32,0.8270000000000017]],"v":[[0,-13.5],[32,18.5],[0,50.5],[-32,18.5]],"c":true}]},{"i":{"x":0.667,"y":1},"o":{"x":0.333,"y":0},"t":24,"s":[{"i":[[-17.423,-23.25],[32.25,-8.922999999999998],[17.923,40.75],[-31.75,26.423]],"o":[[17.923,-23.25],[32.25,26.423],[-17.423,40.75],[-31.75,-8.922999999999998]],"v":[[0.25,-23.25],[32.25,8.75],[0.25,40.75],[-31.75,8.75]],"c":true}]},{"i":{"x":0.667,"y":1},"o":{"x":0.333,"y":0},"t":30,"s":[{"i":[[-17.673,-32],[32,-17.673],[17.673,32],[-32,17.673]],"o":[[17.673,-32],[32,17.673],[-17.673,32],[-32,-17.673]],"v":[[0,-32],[32,0],[0,32],[-32,0]],"c":true}]},{"i":{"x":0.667,"y":1},"o":{"x":0.333,"y":0},"t":45,"s":[{"i":[[-17.673,-13.5],[32,0.8270000000000017],[17.673,50.5],[-32,36.173]],"o":[[17.673,-13.5],[32,36.173],[-17.673,50.5],[-32,0.8270000000000017]],"v":[[0,-13.5],[32,18.5],[0,50.5],[-32,18.5]],"c":true}]},{"i":{"x":0.667,"y":1},"o":{"x":0.333,"y":0},"t":54,"s":[{"i":[[-17.423,-23.25],[32.25,-8.922999999999998],[17.923,40.75],[-31.75,26.423]],"o":[[17.923,-23.25],[32.25,26.423],[-17.423,40.75],[-31.75,-8.922999999999998]],"v":[[0.25,-23.25],[32.25,8.75],[0.25,40.75],[-31.75,8.75]],"c":true}]},{"i":{"x":0.667,"y":1},"o":{"x":0.333,"y":0},"t":60,"s":[{"i":[[-17.673,-32],[32,-17.673],[17.673,32],[-32,17.673]],"o":[[17.673,-32],[32,17.673],[-17.673,32],[-32,-17.673]],"v":[[0,-32],[32,0],[0,32],[-32,0]],"c":true}]},{"i":{"x":0.667,"y":1},"o":{"x":0.333,"y":0},"t":75,"s":[{"i":[[-17.673,-13.5],[32,0.8270000000000017],[17.673,50.5],[-32,36.173]],"o":[[17.673,-13.5],[32,36.173],[-17.673,50.5],[-32,0.8270000000000017]],"v":[[0,-13.5],[32,18.5],[0,50.5],[-32,18.5]],"c":true}]},{"i":{"x":0.667,"y":1},"o":{"x":0.333,"y":0},"t":84,"s":[{"i":[[-17.423,-23.25],[32.25,-8.922999999999998],[17.923,40.75],[-31.75,26.423]],"o":[[17.923,-23.25],[32.25,26.423],[-17.423,40.75],[-31.75,-8.922999999999998]],"v":[[0.25,-23.25],[32.25,8.75],[0.25,40.75],[-31.75,8.75]],"c":true}]},{"i":{"x":0.667,"y":1},"o":{"x":0.333,"y":0},"t":90,"s":[{"i":[[-17.673,-32],[32,-17.673],[17.673,32],[-32,17.673]],"o":[[17.673,-32],[32,17.673],[-17.673,32],[-32,-17.673]],"v":[[0,-32],[32,0],[0,32],[-32,0]],"c":true}]},{"i":{"x":0.833,"y":0.833},"o":{"x":0.333,"y":0},"t":105,"s":[{"i":[[-17.673,-13.5],[32,0.8270000000000017],[17.673,50.5],[-32,36.173]],"o":[[17.673,-13.5],[32,36.173],[-17.673,50.5],[-32,0.8270000000000017]],"v":[[0,-13.5],[32,18.5],[0,50.5],[-32,18.5]],"c":true}]},{"i":{"x":0.667,"y":1},"o":{"x":0.167,"y":0.167},"t":108,"s":[{"i":[[-76.109,0.9769999999999999],[-24.674,6.183],[-29.880999999999997,57.618],[-81.315,52.412000000000006]],"o":[[-41.333,-5.349],[-18.348,40.959],[-64.657,63.943999999999996],[-87.64099999999999,17.636]],"v":[[-58.721,-2.186],[-21.511,23.571],[-47.269,60.781],[-84.478,35.024]],"c":true}]},{"i":{"x":0.667,"y":1},"o":{"x":0.333,"y":0},"t":111,"s":[{"i":[[-17.673,-13.5],[32,0.8270000000000017],[17.673,50.5],[-32,36.173]],"o":[[17.673,-13.5],[32,36.173],[-17.673,50.5],[-32,0.8270000000000017]],"v":[[0,-13.5],[32,18.5],[0,50.5],[-32,18.5]],"c":true}]},{"i":{"x":0.667,"y":1},"o":{"x":0.333,"y":0},"t":114,"s":[{"i":[[-17.423,-23.25],[32.25,-8.922999999999998],[17.923,40.75],[-31.75,26.423]],"o":[[17.923,-23.25],[32.25,26.423],[-17.423,40.75],[-31.75,-8.922999999999998]],"v":[[0.25,-23.25],[32.25,8.75],[0.25,40.75],[-31.75,8.75]],"c":true}]},{"t":120,"s":[{"i":[[-17.673,-32],[32,-17.673],[17.673,32],[-32,17.673]],"o":[[17.673,-32],[32,17.673],[-17.673,32],[-32,-17.673]],"v":[[0,-32],[32,0],[0,32],[-32,0]],"c":true}]}],"ix":2},"nm":"Path 1","mn":"ADBE Vector Shape - Group","hd":false,"_render":true},{"ty":"fl","c":{"a":0,"k":[0.1255,0.1529,0.1725,1],"ix":4},"o":{"a":0,"k":100,"ix":5},"r":1,"bm":0,"nm":"Fill 1","mn":"ADBE Vector Graphic - Fill","hd":false,"_render":true},{"ty":"tr","p":{"a":0,"k":[-101.75,-25.75],"ix":2},"a":{"a":0,"k":[0,0],"ix":1},"s":{"a":0,"k":[100,100],"ix":3},"r":{"a":0,"k":0,"ix":6},"o":{"a":0,"k":100,"ix":7},"sk":{"a":0,"k":0,"ix":4},"sa":{"a":0,"k":0,"ix":5},"nm":"Transform","_render":true}],"nm":"Ellipse 1","np":3,"cix":2,"bm":0,"ix":1,"mn":"ADBE Vector Group","hd":false,"_render":true},{"ty":"gr","it":[{"ind":0,"ty":"sh","ix":1,"ks":{"a":1,"k":[{"i":{"x":0.667,"y":1},"o":{"x":0.333,"y":0},"t":0,"s":[{"i":[[-27.75,7.25],[-44.484,29.347],[-92.5,-6.875]],"o":[[-27.75,7.25],[-82.75,21.875],[-92.5,-6.875]],"v":[[-27.75,7.25],[-61.625,26],[-92.5,-6.875]],"c":false}]},{"i":{"x":0.667,"y":1},"o":{"x":0.333,"y":0},"t":15,"s":[{"i":[[-27.75,24.75],[-44.484,46.597],[-92.5,11.625]],"o":[[-27.75,24.75],[-82.75,39.125],[-92.5,11.625]],"v":[[-27.75,24.75],[-61.625,43.25],[-92.5,11.625]],"c":false}]},{"i":{"x":0.667,"y":1},"o":{"x":0.333,"y":0},"t":24,"s":[{"i":[[-29.375,15.25],[-49.109,39.097],[-92.5,1.875]],"o":[[-29.375,15.25],[-87.375,31.625],[-92.5,1.875]],"v":[[-29.375,15.25],[-66.25,35.75],[-92.5,1.875]],"c":false}]},{"i":{"x":0.667,"y":1},"o":{"x":0.333,"y":0},"t":30,"s":[{"i":[[-27.75,7.25],[-44.484,29.347],[-92.5,-6.875]],"o":[[-27.75,7.25],[-82.75,21.875],[-92.5,-6.875]],"v":[[-27.75,7.25],[-61.625,26],[-92.5,-6.875]],"c":false}]},{"i":{"x":0.667,"y":1},"o":{"x":0.333,"y":0},"t":45,"s":[{"i":[[-27.75,24.75],[-44.484,46.597],[-92.5,11.625]],"o":[[-27.75,24.75],[-82.75,39.125],[-92.5,11.625]],"v":[[-27.75,24.75],[-61.625,43.25],[-92.5,11.625]],"c":false}]},{"i":{"x":0.667,"y":1},"o":{"x":0.333,"y":0},"t":54,"s":[{"i":[[-29.375,15.25],[-49.109,39.097],[-92.5,1.875]],"o":[[-29.375,15.25],[-87.375,31.625],[-92.5,1.875]],"v":[[-29.375,15.25],[-66.25,35.75],[-92.5,1.875]],"c":false}]},{"i":{"x":0.667,"y":1},"o":{"x":0.333,"y":0},"t":60,"s":[{"i":[[-27.75,7.25],[-44.484,29.347],[-92.5,-6.875]],"o":[[-27.75,7.25],[-82.75,21.875],[-92.5,-6.875]],"v":[[-27.75,7.25],[-61.625,26],[-92.5,-6.875]],"c":false}]},{"i":{"x":0.667,"y":1},"o":{"x":0.333,"y":0},"t":75,"s":[{"i":[[-27.75,24.75],[-44.484,46.597],[-92.5,11.625]],"o":[[-27.75,24.75],[-82.75,39.125],[-92.5,11.625]],"v":[[-27.75,24.75],[-61.625,43.25],[-92.5,11.625]],"c":false}]},{"i":{"x":0.667,"y":1},"o":{"x":0.333,"y":0},"t":84,"s":[{"i":[[-29.375,15.25],[-49.109,39.097],[-92.5,1.875]],"o":[[-29.375,15.25],[-87.375,31.625],[-92.5,1.875]],"v":[[-29.375,15.25],[-66.25,35.75],[-92.5,1.875]],"c":false}]},{"i":{"x":0.667,"y":1},"o":{"x":0.333,"y":0},"t":90,"s":[{"i":[[-27.75,7.25],[-44.484,29.347],[-92.5,-6.875]],"o":[[-27.75,7.25],[-82.75,21.875],[-92.5,-6.875]],"v":[[-27.75,7.25],[-61.625,26],[-92.5,-6.875]],"c":false}]},{"i":{"x":0.833,"y":0.833},"o":{"x":0.333,"y":0},"t":105,"s":[{"i":[[-27.75,24.75],[-44.484,46.597],[-92.5,11.625]],"o":[[-27.75,24.75],[-82.75,39.125],[-92.5,11.625]],"v":[[-27.75,24.75],[-61.625,43.25],[-92.5,11.625]],"c":false}]},{"i":{"x":0.667,"y":1},"o":{"x":0.167,"y":0.167},"t":108,"s":[{"i":[[-27.784,24.553],[-72.299,31.805],[-142.272,20.463]],"o":[[-27.784,24.553],[-116.5,28.733],[-142.272,20.463]],"v":[[-27.784,24.553],[-89.721,30.594],[-142.272,20.463]],"c":false}]},{"i":{"x":0.667,"y":1},"o":{"x":0.333,"y":0},"t":111,"s":[{"i":[[-27.75,24.75],[-44.484,46.597],[-92.5,11.625]],"o":[[-27.75,24.75],[-82.75,39.125],[-92.5,11.625]],"v":[[-27.75,24.75],[-61.625,43.25],[-92.5,11.625]],"c":false}]},{"i":{"x":0.667,"y":1},"o":{"x":0.333,"y":0},"t":114,"s":[{"i":[[-29.375,15.25],[-49.109,39.097],[-92.5,1.875]],"o":[[-29.375,15.25],[-87.375,31.625],[-92.5,1.875]],"v":[[-29.375,15.25],[-66.25,35.75],[-92.5,1.875]],"c":false}]},{"t":120,"s":[{"i":[[-27.75,7.25],[-44.484,29.347],[-92.5,-6.875]],"o":[[-27.75,7.25],[-82.75,21.875],[-92.5,-6.875]],"v":[[-27.75,7.25],[-61.625,26],[-92.5,-6.875]],"c":false}]}],"ix":2},"nm":"Path 1","mn":"ADBE Vector Shape - Group","hd":false,"_render":true},{"ty":"st","c":{"a":0,"k":[0.2176,0.3371,0.4224,1],"ix":3},"o":{"a":0,"k":100,"ix":4},"w":{"a":0,"k":15,"ix":5},"lc":2,"lj":1,"ml":4,"bm":0,"nm":"Stroke 1","mn":"ADBE Vector Graphic - Stroke","hd":false,"_render":true},{"ty":"tr","p":{"a":0,"k":[0,0],"ix":2},"a":{"a":0,"k":[0,0],"ix":1},"s":{"a":0,"k":[100,100],"ix":3},"r":{"a":0,"k":0,"ix":6},"o":{"a":0,"k":100,"ix":7},"sk":{"a":0,"k":0,"ix":4},"sa":{"a":0,"k":0,"ix":5},"nm":"Transform","_render":true}],"nm":"Shape 1","np":3,"cix":2,"bm":0,"ix":2,"mn":"ADBE Vector Group","hd":false,"_render":true}],"ip":0,"op":180,"st":0,"ct":1,"bm":0,"completed":true},{"ddd":0,"ind":8,"ty":4,"nm":"Shape Layer 1","sr":1,"ks":{"o":{"a":0,"k":100,"ix":11},"r":{"a":0,"k":0,"ix":10},"p":{"a":0,"k":[230,251.5,0],"ix":2,"l":2},"a":{"a":0,"k":[0,0,0],"ix":1,"l":2},"s":{"a":0,"k":[100,100,100],"ix":6,"l":2}},"ao":0,"shapes":[{"ty":"gr","it":[{"ind":0,"ty":"sh","ix":1,"ks":{"a":1,"k":[{"i":{"x":0.667,"y":1},"o":{"x":0.333,"y":0},"t":0,"s":[{"i":[[-89,182.5],[98.5,182.5]],"o":[[-89,182.5],[98.5,182.5]],"v":[[-89,182.5],[98.5,182.5]],"c":false}]},{"i":{"x":0.667,"y":1},"o":{"x":0.333,"y":0},"t":15,"s":[{"i":[[-104,182.5],[113,182.5]],"o":[[-104,182.5],[113,182.5]],"v":[[-104,182.5],[113,182.5]],"c":false}]},{"i":{"x":0.667,"y":1},"o":{"x":0.333,"y":0},"t":30,"s":[{"i":[[-89,182.5],[98.5,182.5]],"o":[[-89,182.5],[98.5,182.5]],"v":[[-89,182.5],[98.5,182.5]],"c":false}]},{"i":{"x":0.667,"y":1},"o":{"x":0.333,"y":0},"t":45,"s":[{"i":[[-104,182.5],[113,182.5]],"o":[[-104,182.5],[113,182.5]],"v":[[-104,182.5],[113,182.5]],"c":false}]},{"i":{"x":0.667,"y":1},"o":{"x":0.333,"y":0},"t":60,"s":[{"i":[[-89,182.5],[98.5,182.5]],"o":[[-89,182.5],[98.5,182.5]],"v":[[-89,182.5],[98.5,182.5]],"c":false}]},{"i":{"x":0.667,"y":1},"o":{"x":0.333,"y":0},"t":75,"s":[{"i":[[-104,182.5],[113,182.5]],"o":[[-104,182.5],[113,182.5]],"v":[[-104,182.5],[113,182.5]],"c":false}]},{"i":{"x":0.667,"y":1},"o":{"x":0.333,"y":0},"t":90,"s":[{"i":[[-89,182.5],[98.5,182.5]],"o":[[-89,182.5],[98.5,182.5]],"v":[[-89,182.5],[98.5,182.5]],"c":false}]},{"i":{"x":0.667,"y":1},"o":{"x":0.333,"y":0},"t":105,"s":[{"i":[[-104,182.5],[113,182.5]],"o":[[-104,182.5],[113,182.5]],"v":[[-104,182.5],[113,182.5]],"c":false}]},{"t":120,"s":[{"i":[[-89,182.5],[98.5,182.5]],"o":[[-89,182.5],[98.5,182.5]],"v":[[-89,182.5],[98.5,182.5]],"c":false}]}],"ix":2},"nm":"Path 1","mn":"ADBE Vector Shape - Group","hd":false,"_render":true},{"ty":"st","c":{"a":0,"k":[1,0.5569,0.2275,1],"ix":3},"o":{"a":0,"k":100,"ix":4},"w":{"a":0,"k":5,"ix":5},"lc":1,"lj":1,"ml":4,"bm":0,"nm":"Stroke 1","mn":"ADBE Vector Graphic - Stroke","hd":false,"_render":true},{"ty":"tr","p":{"a":0,"k":[0,0],"ix":2},"a":{"a":0,"k":[0,0],"ix":1},"s":{"a":0,"k":[100,100],"ix":3},"r":{"a":0,"k":0,"ix":6},"o":{"a":0,"k":100,"ix":7},"sk":{"a":0,"k":0,"ix":4},"sa":{"a":0,"k":0,"ix":5},"nm":"Transform","_render":true}],"nm":"Shape 1","np":3,"cix":2,"bm":0,"ix":1,"mn":"ADBE Vector Group","hd":false,"_render":true}],"ip":0,"op":180,"st":0,"ct":1,"bm":0,"completed":true}],"markers":[],"props":{},"__complete":true}